discord_typings/__init__.py
discord_typings/gateway.py
discord_typings/py.typed
discord_typings/reference.py
discord_typings/interactions/__init__.py
discord_typings/interactions/commands.py
discord_typings/interactions/components.py
discord_typings/interactions/receiving.py
discord_typings/resources/__init__.py
discord_typings/resources/application.py
discord_typings/resources/audit_log.py
discord_typings/resources/auto_moderation.py
discord_typings/resources/channel.py
discord_typings/resources/emoji.py
discord_typings/resources/guild.py
discord_typings/resources/guild_scheduled_events.py
discord_typings/resources/guild_template.py
discord_typings/resources/invite.py
discord_typings/resources/stage_instance.py
discord_typings/resources/sticker.py
discord_typings/resources/user.py
discord_typings/resources/voice.py
discord_typings/resources/webhook.py
discord_typings-0.5.0.dist-info/LICENSE
discord_typings-0.5.0.dist-info/WHEEL
discord_typings-0.5.0.dist-info/METADATA
discord_typings-0.5.0.dist-info/RECORD
